polyscope_bindings.cpython-36m-darwin.so
tetrapolyscope/__init__.py
tetrapolyscope/camera_view.py
tetrapolyscope/common.py
tetrapolyscope/core.py
tetrapolyscope/curve_network.py
tetrapolyscope/device_interop.py
tetrapolyscope/floating_quantities.py
tetrapolyscope/global_floating_quantity_structure.py
tetrapolyscope/implicit_helpers.py
tetrapolyscope/light.py
tetrapolyscope/managed_buffer.py
tetrapolyscope/point_cloud.py
tetrapolyscope/point_light.py
tetrapolyscope/structure.py
tetrapolyscope/surface_mesh.py
tetrapolyscope/volume_grid.py
tetrapolyscope/volume_mesh.py
tetrapolyscope/imgui/__init__.py
tetrapolyscope-0.0.4.dist-info/LICENSE
tetrapolyscope-0.0.4.dist-info/METADATA
tetrapolyscope-0.0.4.dist-info/WHEEL
tetrapolyscope-0.0.4.dist-info/top_level.txt
tetrapolyscope-0.0.4.dist-info/RECORD
