Metadata-Version: 2.1
Name: tetrapolyscope
Version: 0.0.4
Summary: Polyscope: A viewer and user interface for 3D data.
Home-page: https://polyscope.run
Author: Nicholas Sharp
Author-email: nmwsharp@gmail.com
License: MIT
License-File: LICENSE
Requires-Dist: numpy
